{"version":"1.0.0","commands":{"gulp":{"id":"gulp","description":"Interact with Gulp for task running operations.","pluginName":"@oclif/gsys","pluginType":"core","aliases":[],"flags":{"help":{"name":"help","type":"boolean","char":"h","description":"show CLI help","allowNo":false},"name":{"name":"name","type":"option","char":"n","description":"Interact with Gulp for task running operations."},"force":{"name":"force","type":"boolean","char":"f","allowNo":false}},"args":[{"name":"file"}]},"npm":{"id":"npm","description":"Interact with the npm registry in the scope of this CLI.  i.e.- not globally","pluginName":"@oclif/gsys","pluginType":"core","aliases":[],"examples":["$ gsys npm\nInteract with the npm registry in the scope of this CLI.  i.e.- not globally\n"],"flags":{"help":{"name":"help","type":"boolean","char":"h","description":"show CLI help","allowNo":false},"name":{"name":"name","type":"option","char":"n","description":"Interact with NPM for this CLI scope only!"},"force":{"name":"force","type":"boolean","char":"f","allowNo":false}},"args":[{"name":"file"}]}}}